sphinxcontrib_restbuilder-0.3-py3.8-nspkg.pth
sphinxcontrib/restbuilder.py
sphinxcontrib/builders/__init__.py
sphinxcontrib/builders/rst.py
sphinxcontrib/writers/__init__.py
sphinxcontrib/writers/rst.py
sphinxcontrib_restbuilder-0.3.dist-info/LICENSE.txt
sphinxcontrib_restbuilder-0.3.dist-info/METADATA
sphinxcontrib_restbuilder-0.3.dist-info/WHEEL
sphinxcontrib_restbuilder-0.3.dist-info/namespace_packages.txt
sphinxcontrib_restbuilder-0.3.dist-info/top_level.txt
sphinxcontrib_restbuilder-0.3.dist-info/RECORD
